LICENSE
MANIFEST.in
setup.py
quickD3map/BaseMap.py
quickD3map/LineMap.py
quickD3map/PointMap.py
quickD3map/__init__.py
quickD3map/check_data.py
quickD3map/utilities.py
quickD3map.egg-info/PKG-INFO
quickD3map.egg-info/SOURCES.txt
quickD3map.egg-info/dependency_links.txt
quickD3map.egg-info/not-zip-safe
quickD3map.egg-info/top_level.txt
quickD3map/templates/.DS_Store
quickD3map/templates/colorbrewer.css
quickD3map/templates/colorbrewer.js
quickD3map/templates/d3.geo.projection.v0.min.js
quickD3map/templates/d3.v3.min.js
quickD3map/templates/style.css
quickD3map/templates/topojson.v1.min.js
quickD3map/templates/us_map.html
quickD3map/templates/us_states.json
quickD3map/templates/world-110m.json
quickD3map/templates/world-50m.json
quickD3map/templates/world_map.html
quickD3map/templates/world_map_Line.html
quickD3map/templates/world_map_Line_zoom.html